LICENSE
README.md
pyntc/__init__.py
pyntc/devices/__init__.py
pyntc/devices/aireos_device.py
pyntc/devices/asa_device.py
pyntc/devices/base_device.py
pyntc/devices/eos_device.py
pyntc/devices/f5_device.py
pyntc/devices/ios_device.py
pyntc/devices/iosxewlc_device.py
pyntc/devices/jnpr_device.py
pyntc/devices/nxos_device.py
pyntc/devices/system_features/__init__.py
pyntc/devices/system_features/base_feature.py
pyntc/devices/system_features/vlans/__init__.py
pyntc/devices/system_features/vlans/base_vlans.py
pyntc/devices/system_features/vlans/eos_vlans.py
pyntc/devices/tables/__init__.py
pyntc/devices/tables/jnpr/__init__.py
pyntc/devices/tables/jnpr/loopback.py
pyntc/devices/tables/jnpr/loopback.yml
pyntc/errors.py
pyntc/log.py
pyntc/utils/__init__.py
pyntc/utils/converters.py
pyntc/utils/templates/__init__.py
pyntc/utils/templates/cisco_asa_show_interface.template
pyntc/utils/templates/cisco_asa_show_version.template
pyntc/utils/templates/cisco_ios_show_ip_int_brief.template
pyntc/utils/templates/cisco_ios_show_version.template
pyntc/utils/templates/cisco_ios_show_vlan.template
pyntc-2.0.1.dist-info/LICENSE
pyntc-2.0.1.dist-info/METADATA
pyntc-2.0.1.dist-info/WHEEL
pyntc-2.0.1.dist-info/entry_points.txt
pyntc-2.0.1.dist-info/RECORD
