Metadata-Version: 2.1
Name: pyntc
Version: 2.0.1
Summary: SDK to simplify common workflows for Network Devices.
Home-page: https://pyntc.readthedocs.io
License: Apache-2.0
Keywords: network,os-upgrades,network devices
Author: Network to Code, LLC
Author-email: info@networktocode.com
Requires-Python: >=3.8,<4.0
Classifier: Development Status :: 4 - Beta
Classifier: Intended Audience :: Developers
Classifier: License :: OSI Approved :: Apache Software License
Classifier: Programming Language :: Python :: 3
Classifier: Programming Language :: Python :: 3.8
Classifier: Programming Language :: Python :: 3.9
Classifier: Programming Language :: Python :: 3.10
Classifier: Programming Language :: Python :: 3.11
Classifier: Programming Language :: Python :: 3.12
Classifier: Programming Language :: Python :: 3.7
Requires-Dist: f5-sdk (>=3.0.21,<4.0.0)
Requires-Dist: junos-eznc (>=2.6,<3.0)
Requires-Dist: netmiko (>=4.0,<5.0)
Requires-Dist: pyeapi (>=1.0.2,<2.0.0)
Requires-Dist: pynxos (>=0.0.5,<0.0.6)
Requires-Dist: requests (>=2.28,<3.0)
Requires-Dist: scp (>=0.14,<0.15)
Project-URL: Documentation, https://pyntc.readthedocs.io
Project-URL: Repository, https://github.com/networktocode/pyntc
